{
	"Version": 3,
	"Meta": {
		"Duration": 4.567,
		"Fps": 30.0,
		"Loop": true,
		"AreBeziersRestricted": true,
		"CurveCount": 35,
		"TotalSegmentCount": 516,
		"TotalPointCount": 1581,
		"UserDataCount": 0,
		"TotalUserDataSize": 0
	},
	"Curves": [
		{
			"Target": "Parameter",
			"Id": "Param",
			"Segments": [
				0,
				7,
				1,
				1.522,
				7,
				3.044,
				7,
				4.567,
				7
			]
		},
		{
			"Target": "Parameter",
			"Id": "Param2",
			"Segments": [
				0,
				-4.5,
				1,
				1.522,
				-4.5,
				3.044,
				-4.5,
				4.567,
				-4.5
			]
		},
		{
			"Target": "Parameter",
			"Id": "Param3",
			"Segments": [
				0,
				-2,
				1,
				1.522,
				-2,
				3.044,
				-2,
				4.567,
				-2
			]
		},
		{
			"Target": "Parameter",
			"Id": "ParamEyeLOpen",
			"Segments": [
				0,
				0.7,
				1,
				0.167,
				0.7,
				0.333,
				1,
				0.5,
				1,
				1,
				0.533,
				1,
				0.567,
				0,
				0.6,
				0,
				1,
				0.878,
				0,
				1.156,
				0,
				1.433,
				0,
				1,
				1.5,
				0,
				1.567,
				1,
				1.633,
				1,
				1,
				1.778,
				1,
				1.922,
				1,
				2.067,
				1,
				1,
				2.1,
				1,
				2.133,
				0,
				2.167,
				0,
				1,
				2.233,
				0,
				2.3,
				1,
				2.367,
				1,
				1,
				2.789,
				1,
				3.211,
				1,
				3.633,
				1,
				1,
				3.711,
				1,
				3.789,
				0,
				3.867,
				0,
				1,
				3.911,
				0,
				3.956,
				1,
				4,
				1,
				1,
				4.189,
				1,
				4.378,
				0.7,
				4.567,
				0.7
			]
		},
		{
			"Target": "Parameter",
			"Id": "ParamEyeLSmile",
			"Segments": [
				0,
				1,
				1,
				0.478,
				1,
				0.956,
				0.5,
				1.433,
				0.5,
				1,
				2.478,
				0.5,
				3.522,
				1,
				4.567,
				1
			]
		},
		{
			"Target": "Parameter",
			"Id": "ParamEyeBallX",
			"Segments": [
				0,
				0,
				1,
				1.522,
				0,
				3.044,
				0,
				4.567,
				0
			]
		},
		{
			"Target": "Parameter",
			"Id": "ParamEyeBallY",
			"Segments": [
				0,
				0,
				1,
				1.522,
				0,
				3.044,
				0,
				4.567,
				0
			]
		},
		{
			"Target": "Parameter",
			"Id": "ParamBrowRForm",
			"Segments": [
				0,
				-1,
				1,
				1.522,
				-1,
				3.044,
				-1,
				4.567,
				-1
			]
		},
		{
			"Target": "Parameter",
			"Id": "ParamMouthForm",
			"Segments": [
				0,
				0,
				1,
				1.522,
				0,
				3.044,
				0,
				4.567,
				0
			]
		},
		{
			"Target": "Parameter",
			"Id": "ParamMouthOpenY",
			"Segments": [
				0,
				0.407,
				1,
				0.033,
				0.289,
				0.067,
				0.2,
				0.1,
				0.2,
				1,
				0.178,
				0.2,
				0.256,
				1,
				0.333,
				1,
				1,
				0.433,
				1,
				0.533,
				0.2,
				0.633,
				0.2,
				1,
				0.711,
				0.2,
				0.789,
				1,
				0.867,
				1,
				1,
				0.967,
				1,
				1.067,
				0.2,
				1.167,
				0.2,
				1,
				1.244,
				0.2,
				1.322,
				1,
				1.4,
				1,
				1,
				1.5,
				1,
				1.6,
				0.2,
				1.7,
				0.2,
				1,
				1.778,
				0.2,
				1.856,
				1,
				1.933,
				1,
				1,
				2.033,
				1,
				2.133,
				0.2,
				2.233,
				0.2,
				1,
				2.311,
				0.2,
				2.389,
				1,
				2.467,
				1,
				1,
				2.567,
				1,
				2.667,
				0.2,
				2.767,
				0.2,
				1,
				2.844,
				0.2,
				2.922,
				1,
				3,
				1,
				1,
				3.1,
				1,
				3.2,
				0.2,
				3.3,
				0.2,
				1,
				3.378,
				0.2,
				3.456,
				1,
				3.533,
				1,
				1,
				3.633,
				1,
				3.733,
				0.2,
				3.833,
				0.2,
				1,
				3.911,
				0.2,
				3.989,
				1,
				4.067,
				1,
				1,
				4.167,
				1,
				4.267,
				0.2,
				4.367,
				0.2,
				1,
				4.433,
				0.2,
				4.5,
				0.788,
				4.567,
				0.956
			]
		},
		{
			"Target": "Parameter",
			"Id": "ParamCheek",
			"Segments": [
				0,
				1,
				1,
				1.522,
				1,
				3.044,
				1,
				4.567,
				1
			]
		},
		{
			"Target": "Parameter",
			"Id": "Param16",
			"Segments": [
				0,
				19,
				1,
				0.033,
				19,
				0.067,
				-16,
				0.1,
				-16,
				1,
				0.144,
				-16,
				0.189,
				19,
				0.233,
				19,
				1,
				0.278,
				19,
				0.322,
				-16,
				0.367,
				-16,
				1,
				0.411,
				-16,
				0.456,
				19,
				0.5,
				19,
				1,
				0.533,
				19,
				0.567,
				-16,
				0.6,
				-16,
				1,
				0.644,
				-16,
				0.689,
				19,
				0.733,
				19,
				1,
				0.767,
				19,
				0.8,
				-16,
				0.833,
				-16,
				1,
				0.878,
				-16,
				0.922,
				19,
				0.967,
				19,
				1,
				1,
				19,
				1.033,
				-16,
				1.067,
				-16,
				1,
				1.111,
				-16,
				1.156,
				19,
				1.2,
				19,
				1,
				1.233,
				19,
				1.267,
				-16,
				1.3,
				-16,
				1,
				1.344,
				-16,
				1.389,
				19,
				1.433,
				19,
				1,
				1.478,
				19,
				1.522,
				-16,
				1.567,
				-16,
				1,
				1.611,
				-16,
				1.656,
				19,
				1.7,
				19,
				1,
				1.733,
				19,
				1.767,
				-16,
				1.8,
				-16,
				1,
				1.844,
				-16,
				1.889,
				19,
				1.933,
				19,
				1,
				1.967,
				19,
				2,
				-16,
				2.033,
				-16,
				1,
				2.078,
				-16,
				2.122,
				19,
				2.167,
				19,
				1,
				2.2,
				19,
				2.233,
				-16,
				2.267,
				-16,
				1,
				2.311,
				-16,
				2.356,
				19,
				2.4,
				19,
				1,
				2.433,
				19,
				2.467,
				-16,
				2.5,
				-16,
				1,
				2.544,
				-16,
				2.589,
				19,
				2.633,
				19,
				1,
				2.678,
				19,
				2.722,
				-16,
				2.767,
				-16,
				1,
				2.811,
				-16,
				2.856,
				19,
				2.9,
				19,
				1,
				2.933,
				19,
				2.967,
				-16,
				3,
				-16,
				1,
				3.044,
				-16,
				3.089,
				19,
				3.133,
				19,
				1,
				3.167,
				19,
				3.2,
				-16,
				3.233,
				-16,
				1,
				3.278,
				-16,
				3.322,
				19,
				3.367,
				19,
				1,
				3.4,
				19,
				3.433,
				-16,
				3.467,
				-16,
				1,
				3.511,
				-16,
				3.556,
				19,
				3.6,
				19,
				1,
				3.633,
				19,
				3.667,
				-16,
				3.7,
				-16,
				1,
				3.744,
				-16,
				3.789,
				19,
				3.833,
				19,
				1,
				3.878,
				19,
				3.922,
				-16,
				3.967,
				-16,
				1,
				4.011,
				-16,
				4.056,
				19,
				4.1,
				19,
				1,
				4.133,
				19,
				4.167,
				-16,
				4.2,
				-16,
				1,
				4.244,
				-16,
				4.289,
				19,
				4.333,
				19,
				1,
				4.367,
				19,
				4.4,
				-16,
				4.433,
				-16,
				1,
				4.478,
				-16,
				4.522,
				19,
				4.567,
				19
			]
		},
		{
			"Target": "Parameter",
			"Id": "Param27",
			"Segments": [
				0,
				1,
				1,
				1.522,
				1,
				3.044,
				1,
				4.567,
				1
			]
		},
		{
			"Target": "Parameter",
			"Id": "ParamAngleY",
			"Segments": [
				0,
				5.4,
				1,
				0.056,
				-7.494,
				0.111,
				-22,
				0.167,
				-22,
				1,
				0.233,
				-22,
				0.3,
				25,
				0.367,
				25,
				1,
				0.467,
				25,
				0.567,
				-22,
				0.667,
				-22,
				1,
				0.744,
				-22,
				0.822,
				25,
				0.9,
				25,
				1,
				0.989,
				25,
				1.078,
				-22,
				1.167,
				-22,
				1,
				1.244,
				-22,
				1.322,
				25,
				1.4,
				25,
				1,
				1.5,
				25,
				1.6,
				-22,
				1.7,
				-22,
				1,
				1.767,
				-22,
				1.833,
				25,
				1.9,
				25,
				1,
				2,
				25,
				2.1,
				-22,
				2.2,
				-22,
				1,
				2.267,
				-22,
				2.333,
				25,
				2.4,
				25,
				1,
				2.5,
				25,
				2.6,
				-22,
				2.7,
				-22,
				1,
				2.767,
				-22,
				2.833,
				25,
				2.9,
				25,
				1,
				3,
				25,
				3.1,
				-22,
				3.2,
				-22,
				1,
				3.278,
				-22,
				3.356,
				25,
				3.433,
				25,
				1,
				3.522,
				25,
				3.611,
				-22,
				3.7,
				-22,
				1,
				3.778,
				-22,
				3.856,
				25,
				3.933,
				25,
				1,
				4.033,
				25,
				4.133,
				-22,
				4.233,
				-22,
				1,
				4.3,
				-22,
				4.367,
				25,
				4.433,
				25,
				1,
				4.478,
				25,
				4.522,
				15.716,
				4.567,
				5.4
			]
		},
		{
			"Target": "Parameter",
			"Id": "Paramnv",
			"Segments": [
				0,
				-11.016,
				1,
				0.033,
				-21.563,
				0.067,
				-30,
				0.1,
				-30,
				1,
				0.178,
				-30,
				0.256,
				30,
				0.333,
				30,
				1,
				0.433,
				30,
				0.533,
				-30,
				0.633,
				-30,
				1,
				0.7,
				-30,
				0.767,
				30,
				0.833,
				30,
				1,
				0.933,
				30,
				1.033,
				-30,
				1.133,
				-30,
				1,
				1.2,
				-30,
				1.267,
				30,
				1.333,
				30,
				1,
				1.433,
				30,
				1.533,
				-30,
				1.633,
				-30,
				1,
				1.7,
				-30,
				1.767,
				30,
				1.833,
				30,
				1,
				1.933,
				30,
				2.033,
				-30,
				2.133,
				-30,
				1,
				2.211,
				-30,
				2.289,
				30,
				2.367,
				30,
				1,
				2.456,
				30,
				2.544,
				-30,
				2.633,
				-30,
				1,
				2.711,
				-30,
				2.789,
				30,
				2.867,
				30,
				1,
				2.967,
				30,
				3.067,
				-30,
				3.167,
				-30,
				1,
				3.233,
				-30,
				3.3,
				30,
				3.367,
				30,
				1,
				3.467,
				30,
				3.567,
				-30,
				3.667,
				-30,
				1,
				3.733,
				-30,
				3.8,
				30,
				3.867,
				30,
				1,
				3.967,
				30,
				4.067,
				-30,
				4.167,
				-30,
				1,
				4.233,
				-30,
				4.3,
				30,
				4.367,
				30,
				1,
				4.433,
				30,
				4.5,
				3.333,
				4.567,
				-14.445
			]
		},
		{
			"Target": "Parameter",
			"Id": "Paramnv2",
			"Segments": [
				0,
				0,
				1,
				1.522,
				0,
				3.044,
				0,
				4.567,
				0
			]
		},
		{
			"Target": "Parameter",
			"Id": "Paramnan2",
			"Segments": [
				0,
				-20,
				1,
				0.067,
				-20,
				0.133,
				30,
				0.2,
				30,
				1,
				0.3,
				30,
				0.4,
				-20,
				0.5,
				-20,
				1,
				0.567,
				-20,
				0.633,
				30,
				0.7,
				30,
				1,
				0.811,
				30,
				0.922,
				-20,
				1.033,
				-20,
				1,
				1.089,
				-20,
				1.144,
				30,
				1.2,
				30,
				1,
				1.311,
				30,
				1.422,
				-20,
				1.533,
				-20,
				1,
				1.589,
				-20,
				1.644,
				30,
				1.7,
				30,
				1,
				1.811,
				30,
				1.922,
				-20,
				2.033,
				-20,
				1,
				2.1,
				-20,
				2.167,
				30,
				2.233,
				30,
				1,
				2.333,
				30,
				2.433,
				-20,
				2.533,
				-20,
				1,
				2.6,
				-20,
				2.667,
				30,
				2.733,
				30,
				1,
				2.833,
				30,
				2.933,
				-20,
				3.033,
				-20,
				1,
				3.1,
				-20,
				3.167,
				30,
				3.233,
				30,
				1,
				3.344,
				30,
				3.456,
				-20,
				3.567,
				-20,
				1,
				3.622,
				-20,
				3.678,
				30,
				3.733,
				30,
				1,
				3.844,
				30,
				3.956,
				-20,
				4.067,
				-20,
				1,
				4.122,
				-20,
				4.178,
				30,
				4.233,
				30,
				1,
				4.344,
				30,
				4.456,
				-20,
				4.567,
				-20
			]
		},
		{
			"Target": "Parameter",
			"Id": "Paramnan",
			"Segments": [
				0,
				-13.12,
				1,
				0.033,
				-20.05,
				0.067,
				-25,
				0.1,
				-25,
				1,
				0.156,
				-25,
				0.211,
				30,
				0.267,
				30,
				1,
				0.378,
				30,
				0.489,
				-25,
				0.6,
				-25,
				1,
				0.656,
				-25,
				0.711,
				30,
				0.767,
				30,
				1,
				0.878,
				30,
				0.989,
				-25,
				1.1,
				-25,
				1,
				1.167,
				-25,
				1.233,
				30,
				1.3,
				30,
				1,
				1.4,
				30,
				1.5,
				-25,
				1.6,
				-25,
				1,
				1.667,
				-25,
				1.733,
				30,
				1.8,
				30,
				1,
				1.9,
				30,
				2,
				-25,
				2.1,
				-25,
				1,
				2.167,
				-25,
				2.233,
				30,
				2.3,
				30,
				1,
				2.411,
				30,
				2.522,
				-25,
				2.633,
				-25,
				1,
				2.689,
				-25,
				2.744,
				30,
				2.8,
				30,
				1,
				2.911,
				30,
				3.022,
				-25,
				3.133,
				-25,
				1,
				3.189,
				-25,
				3.244,
				30,
				3.3,
				30,
				1,
				3.411,
				30,
				3.522,
				-25,
				3.633,
				-25,
				1,
				3.7,
				-25,
				3.767,
				30,
				3.833,
				30,
				1,
				3.933,
				30,
				4.033,
				-25,
				4.133,
				-25,
				1,
				4.2,
				-25,
				4.267,
				30,
				4.333,
				30,
				1,
				4.411,
				30,
				4.489,
				-3.272,
				4.567,
				-18.059
			]
		},
		{
			"Target": "Parameter",
			"Id": "Param8",
			"Segments": [
				0,
				30,
				1,
				0.011,
				30,
				0.022,
				30,
				0.033,
				30,
				1,
				0.078,
				30,
				0.122,
				-30,
				0.167,
				-30,
				1,
				0.2,
				-30,
				0.233,
				-30,
				0.267,
				-30,
				1,
				0.322,
				-30,
				0.378,
				30,
				0.433,
				30,
				1,
				0.467,
				30,
				0.5,
				30,
				0.533,
				30,
				1,
				0.589,
				30,
				0.644,
				-30,
				0.7,
				-30,
				1,
				0.733,
				-30,
				0.767,
				-30,
				0.8,
				-30,
				1,
				0.856,
				-30,
				0.911,
				30,
				0.967,
				30,
				1,
				0.989,
				30,
				1.011,
				30,
				1.033,
				30,
				1,
				1.089,
				30,
				1.144,
				-30,
				1.2,
				-30,
				1,
				1.233,
				-30,
				1.267,
				-30,
				1.3,
				-30,
				1,
				1.356,
				-30,
				1.411,
				30,
				1.467,
				30,
				1,
				1.489,
				30,
				1.511,
				30,
				1.533,
				30,
				1,
				1.589,
				30,
				1.644,
				-30,
				1.7,
				-30,
				1,
				1.733,
				-30,
				1.767,
				-30,
				1.8,
				-30,
				1,
				1.856,
				-30,
				1.911,
				30,
				1.967,
				30,
				1,
				1.989,
				30,
				2.011,
				30,
				2.033,
				30,
				1,
				2.089,
				30,
				2.144,
				-30,
				2.2,
				-30,
				1,
				2.233,
				-30,
				2.267,
				-30,
				2.3,
				-30,
				1,
				2.356,
				-30,
				2.411,
				30,
				2.467,
				30,
				1,
				2.5,
				30,
				2.533,
				30,
				2.567,
				30,
				1,
				2.622,
				30,
				2.678,
				-30,
				2.733,
				-30,
				1,
				2.767,
				-30,
				2.8,
				-30,
				2.833,
				-30,
				1,
				2.878,
				-30,
				2.922,
				30,
				2.967,
				30,
				1,
				3,
				30,
				3.033,
				30,
				3.067,
				30,
				1,
				3.122,
				30,
				3.178,
				-30,
				3.233,
				-30,
				1,
				3.267,
				-30,
				3.3,
				-30,
				3.333,
				-30,
				1,
				3.389,
				-30,
				3.444,
				30,
				3.5,
				30,
				1,
				3.522,
				30,
				3.544,
				30,
				3.567,
				30,
				1,
				3.622,
				30,
				3.678,
				-30,
				3.733,
				-30,
				1,
				3.767,
				-30,
				3.8,
				-30,
				3.833,
				-30,
				1,
				3.889,
				-30,
				3.944,
				30,
				4,
				30,
				1,
				4.022,
				30,
				4.044,
				30,
				4.067,
				30,
				1,
				4.122,
				30,
				4.178,
				-30,
				4.233,
				-30,
				1,
				4.267,
				-30,
				4.3,
				-30,
				4.333,
				-30,
				1,
				4.389,
				-30,
				4.444,
				30,
				4.5,
				30,
				1,
				4.522,
				30,
				4.544,
				30,
				4.567,
				30
			]
		},
		{
			"Target": "Parameter",
			"Id": "Param28",
			"Segments": [
				0,
				3.331,
				1,
				0.033,
				-2.246,
				0.067,
				-12,
				0.1,
				-12,
				1,
				0.122,
				-12,
				0.144,
				-12.026,
				0.167,
				-10,
				1,
				0.2,
				-6.961,
				0.233,
				2.216,
				0.267,
				5,
				1,
				0.3,
				7.784,
				0.333,
				8,
				0.367,
				8,
				1,
				0.4,
				8,
				0.433,
				8.245,
				0.467,
				7,
				1,
				0.511,
				5.341,
				0.556,
				-12,
				0.6,
				-12,
				1,
				0.622,
				-12,
				0.644,
				-12.026,
				0.667,
				-10,
				1,
				0.7,
				-6.961,
				0.733,
				2.938,
				0.767,
				5,
				1,
				0.811,
				7.749,
				0.856,
				8,
				0.9,
				8,
				1,
				0.922,
				8,
				0.944,
				8.441,
				0.967,
				7,
				1,
				1.011,
				4.119,
				1.056,
				-12,
				1.1,
				-12,
				1,
				1.122,
				-12,
				1.144,
				-11.908,
				1.167,
				-10,
				1,
				1.211,
				-6.183,
				1.256,
				1.415,
				1.3,
				5,
				1,
				1.333,
				7.689,
				1.367,
				8,
				1.4,
				8,
				1,
				1.422,
				8,
				1.444,
				8.441,
				1.467,
				7,
				1,
				1.511,
				4.119,
				1.556,
				-12,
				1.6,
				-12,
				1,
				1.633,
				-12,
				1.667,
				-12,
				1.7,
				-10,
				1,
				1.733,
				-8,
				1.767,
				2.216,
				1.8,
				5,
				1,
				1.833,
				7.784,
				1.867,
				8,
				1.9,
				8,
				1,
				1.922,
				8,
				1.944,
				8.441,
				1.967,
				7,
				1,
				2.011,
				4.119,
				2.056,
				-12,
				2.1,
				-12,
				1,
				2.133,
				-12,
				2.167,
				-12,
				2.2,
				-10,
				1,
				2.233,
				-8,
				2.267,
				2.216,
				2.3,
				5,
				1,
				2.333,
				7.784,
				2.367,
				8,
				2.4,
				8,
				1,
				2.433,
				8,
				2.467,
				8.245,
				2.5,
				7,
				1,
				2.544,
				5.341,
				2.589,
				-12,
				2.633,
				-12,
				1,
				2.656,
				-12,
				2.678,
				-12.026,
				2.7,
				-10,
				1,
				2.733,
				-6.961,
				2.767,
				2.216,
				2.8,
				5,
				1,
				2.833,
				7.784,
				2.867,
				8,
				2.9,
				8,
				1,
				2.933,
				8,
				2.967,
				8.245,
				3,
				7,
				1,
				3.044,
				5.341,
				3.089,
				-12,
				3.133,
				-12,
				1,
				3.156,
				-12,
				3.178,
				-12.026,
				3.2,
				-10,
				1,
				3.233,
				-6.961,
				3.267,
				2.938,
				3.3,
				5,
				1,
				3.344,
				7.749,
				3.389,
				8,
				3.433,
				8,
				1,
				3.456,
				8,
				3.478,
				8.441,
				3.5,
				7,
				1,
				3.544,
				4.119,
				3.589,
				-12,
				3.633,
				-12,
				1,
				3.656,
				-12,
				3.678,
				-11.908,
				3.7,
				-10,
				1,
				3.744,
				-6.183,
				3.789,
				1.415,
				3.833,
				5,
				1,
				3.867,
				7.689,
				3.9,
				8,
				3.933,
				8,
				1,
				3.956,
				8,
				3.978,
				8.441,
				4,
				7,
				1,
				4.044,
				4.119,
				4.089,
				-12,
				4.133,
				-12,
				1,
				4.167,
				-12,
				4.2,
				-12,
				4.233,
				-10,
				1,
				4.267,
				-8,
				4.3,
				2.216,
				4.333,
				5,
				1,
				4.367,
				7.784,
				4.4,
				8,
				4.433,
				8,
				1,
				4.456,
				8,
				4.478,
				8.441,
				4.5,
				7,
				1,
				4.522,
				5.559,
				4.544,
				0.809,
				4.567,
				-3.581
			]
		},
		{
			"Target": "Parameter",
			"Id": "Param29",
			"Segments": [
				0,
				-1.36,
				1,
				0.033,
				-6.4,
				0.067,
				-10,
				0.1,
				-10,
				1,
				0.156,
				-10,
				0.211,
				30,
				0.267,
				30,
				1,
				0.378,
				30,
				0.489,
				-10,
				0.6,
				-10,
				1,
				0.656,
				-10,
				0.711,
				30,
				0.767,
				30,
				1,
				0.878,
				30,
				0.989,
				-10,
				1.1,
				-10,
				1,
				1.167,
				-10,
				1.233,
				30,
				1.3,
				30,
				1,
				1.4,
				30,
				1.5,
				-10,
				1.6,
				-10,
				1,
				1.667,
				-10,
				1.733,
				30,
				1.8,
				30,
				1,
				1.9,
				30,
				2,
				-10,
				2.1,
				-10,
				1,
				2.167,
				-10,
				2.233,
				30,
				2.3,
				30,
				1,
				2.411,
				30,
				2.522,
				-10,
				2.633,
				-10,
				1,
				2.689,
				-10,
				2.744,
				30,
				2.8,
				30,
				1,
				2.911,
				30,
				3.022,
				-10,
				3.133,
				-10,
				1,
				3.189,
				-10,
				3.244,
				30,
				3.3,
				30,
				1,
				3.411,
				30,
				3.522,
				-10,
				3.633,
				-10,
				1,
				3.7,
				-10,
				3.767,
				30,
				3.833,
				30,
				1,
				3.933,
				30,
				4.033,
				-10,
				4.133,
				-10,
				1,
				4.2,
				-10,
				4.267,
				30,
				4.333,
				30,
				1,
				4.411,
				30,
				4.489,
				5.802,
				4.567,
				-4.952
			]
		},
		{
			"Target": "Parameter",
			"Id": "Param13",
			"Segments": [
				0,
				0,
				1,
				1.522,
				0,
				3.044,
				0,
				4.567,
				0
			]
		},
		{
			"Target": "Parameter",
			"Id": "Param21",
			"Segments": [
				0,
				-13.464,
				1,
				0.022,
				-17.749,
				0.044,
				-20.605,
				0.067,
				-20.605,
				1,
				0.144,
				-20.605,
				0.222,
				24.12,
				0.3,
				24.12,
				1,
				0.4,
				24.12,
				0.5,
				-21.904,
				0.6,
				-21.904,
				1,
				0.678,
				-21.904,
				0.756,
				23.74,
				0.833,
				23.74,
				1,
				0.922,
				23.74,
				1.011,
				-21.32,
				1.1,
				-21.32,
				1,
				1.178,
				-21.32,
				1.256,
				24.171,
				1.333,
				24.171,
				1,
				1.422,
				24.171,
				1.511,
				-20.965,
				1.6,
				-20.965,
				1,
				1.678,
				-20.965,
				1.756,
				24.37,
				1.833,
				24.37,
				1,
				1.922,
				24.37,
				2.011,
				-20.802,
				2.1,
				-20.802,
				1,
				2.178,
				-20.802,
				2.256,
				24.844,
				2.333,
				24.844,
				1,
				2.422,
				24.844,
				2.511,
				-20.725,
				2.6,
				-20.725,
				1,
				2.678,
				-20.725,
				2.756,
				24.059,
				2.833,
				24.059,
				1,
				2.933,
				24.059,
				3.033,
				-21.939,
				3.133,
				-21.939,
				1,
				3.211,
				-21.939,
				3.289,
				23.722,
				3.367,
				23.722,
				1,
				3.456,
				23.722,
				3.544,
				-21.334,
				3.633,
				-21.334,
				1,
				3.711,
				-21.334,
				3.789,
				24.163,
				3.867,
				24.163,
				1,
				3.956,
				24.163,
				4.044,
				-20.971,
				4.133,
				-20.971,
				1,
				4.211,
				-20.971,
				4.289,
				24.366,
				4.367,
				24.366,
				1,
				4.433,
				24.366,
				4.5,
				-1.043,
				4.567,
				-13.748
			]
		},
		{
			"Target": "Parameter",
			"Id": "ParamBodyAngleY",
			"Segments": [
				0,
				4.945,
				1,
				0.022,
				6.488,
				0.044,
				7.516,
				0.067,
				7.516,
				1,
				0.144,
				7.516,
				0.222,
				-8.462,
				0.3,
				-8.462,
				1,
				0.4,
				-8.462,
				0.5,
				7.814,
				0.6,
				7.814,
				1,
				0.678,
				7.814,
				0.756,
				-8.403,
				0.833,
				-8.403,
				1,
				0.922,
				-8.403,
				1.011,
				7.631,
				1.1,
				7.631,
				1,
				1.178,
				7.631,
				1.256,
				-8.494,
				1.333,
				-8.494,
				1,
				1.422,
				-8.494,
				1.511,
				7.571,
				1.6,
				7.571,
				1,
				1.678,
				7.571,
				1.756,
				-8.522,
				1.833,
				-8.522,
				1,
				1.922,
				-8.522,
				2.011,
				7.553,
				2.1,
				7.553,
				1,
				2.178,
				7.553,
				2.256,
				-8.631,
				2.333,
				-8.631,
				1,
				2.422,
				-8.631,
				2.511,
				7.701,
				2.6,
				7.701,
				1,
				2.678,
				7.701,
				2.756,
				-8.37,
				2.833,
				-8.37,
				1,
				2.933,
				-8.37,
				3.033,
				7.856,
				3.133,
				7.856,
				1,
				3.211,
				7.856,
				3.289,
				-8.383,
				3.367,
				-8.383,
				1,
				3.456,
				-8.383,
				3.544,
				7.643,
				3.633,
				7.643,
				1,
				3.711,
				7.643,
				3.789,
				-8.489,
				3.867,
				-8.489,
				1,
				3.956,
				-8.489,
				4.044,
				7.575,
				4.133,
				7.575,
				1,
				4.211,
				7.575,
				4.289,
				-8.521,
				4.367,
				-8.521,
				1,
				4.433,
				-8.52,
				4.5,
				0.521,
				4.567,
				5.042
			]
		},
		{
			"Target": "Parameter",
			"Id": "Param4",
			"Segments": [
				0,
				-6.958,
				1,
				0.056,
				2.794,
				0.111,
				15.797,
				0.167,
				15.797,
				1,
				0.256,
				15.797,
				0.344,
				-15.862,
				0.433,
				-15.862,
				1,
				0.522,
				-15.862,
				0.611,
				16.116,
				0.7,
				16.116,
				1,
				0.778,
				16.116,
				0.856,
				-16.58,
				0.933,
				-16.58,
				1,
				1.022,
				-16.58,
				1.111,
				15.557,
				1.2,
				15.557,
				1,
				1.278,
				15.557,
				1.356,
				-16.278,
				1.433,
				-16.278,
				1,
				1.522,
				-16.278,
				1.611,
				15.618,
				1.7,
				15.618,
				1,
				1.778,
				15.618,
				1.856,
				-16.293,
				1.933,
				-16.293,
				1,
				2.022,
				-16.293,
				2.111,
				15.341,
				2.2,
				15.341,
				1,
				2.278,
				15.341,
				2.356,
				-17.049,
				2.433,
				-17.049,
				1,
				2.522,
				-17.049,
				2.611,
				15.927,
				2.7,
				15.927,
				1,
				2.789,
				15.927,
				2.878,
				-15.845,
				2.967,
				-15.845,
				1,
				3.056,
				-15.845,
				3.144,
				16.116,
				3.233,
				16.116,
				1,
				3.311,
				16.116,
				3.389,
				-16.579,
				3.467,
				-16.579,
				1,
				3.556,
				-16.579,
				3.644,
				15.557,
				3.733,
				15.557,
				1,
				3.811,
				15.557,
				3.889,
				-16.278,
				3.967,
				-16.278,
				1,
				4.056,
				-16.278,
				4.144,
				15.618,
				4.233,
				15.618,
				1,
				4.311,
				15.618,
				4.389,
				-16.293,
				4.467,
				-16.293,
				1,
				4.5,
				-16.293,
				4.533,
				-11.844,
				4.567,
				-6.284
			]
		},
		{
			"Target": "Parameter",
			"Id": "Param6",
			"Segments": [
				0,
				-14.173,
				1,
				0.089,
				-14.173,
				0.178,
				13.209,
				0.267,
				13.209,
				1,
				0.356,
				13.209,
				0.444,
				-12.901,
				0.533,
				-12.901,
				1,
				0.611,
				-12.901,
				0.689,
				14.277,
				0.767,
				14.277,
				1,
				0.856,
				14.277,
				0.944,
				-12.864,
				1.033,
				-12.864,
				1,
				1.111,
				-12.864,
				1.189,
				13.359,
				1.267,
				13.359,
				1,
				1.356,
				13.359,
				1.444,
				-12.541,
				1.533,
				-12.541,
				1,
				1.611,
				-12.541,
				1.689,
				13.409,
				1.767,
				13.409,
				1,
				1.856,
				13.409,
				1.944,
				-12.584,
				2.033,
				-12.584,
				1,
				2.111,
				-12.584,
				2.189,
				13.422,
				2.267,
				13.422,
				1,
				2.356,
				13.422,
				2.444,
				-13.752,
				2.533,
				-13.752,
				1,
				2.622,
				-13.752,
				2.711,
				13.296,
				2.8,
				13.296,
				1,
				2.889,
				13.296,
				2.978,
				-12.922,
				3.067,
				-12.922,
				1,
				3.144,
				-12.922,
				3.222,
				14.277,
				3.3,
				14.277,
				1,
				3.389,
				14.277,
				3.478,
				-12.864,
				3.567,
				-12.864,
				1,
				3.644,
				-12.864,
				3.722,
				13.359,
				3.8,
				13.359,
				1,
				3.889,
				13.359,
				3.978,
				-12.541,
				4.067,
				-12.541,
				1,
				4.144,
				-12.541,
				4.222,
				13.409,
				4.3,
				13.409,
				1,
				4.389,
				13.409,
				4.478,
				-12.584,
				4.567,
				-12.584
			]
		},
		{
			"Target": "Parameter",
			"Id": "Param5",
			"Segments": [
				0,
				11.039,
				1,
				0.011,
				11.743,
				0.022,
				12.145,
				0.033,
				12.145,
				1,
				0.111,
				12.145,
				0.189,
				-12.876,
				0.267,
				-12.876,
				1,
				0.356,
				-12.876,
				0.444,
				11.593,
				0.533,
				11.593,
				1,
				0.622,
				11.593,
				0.711,
				-14.023,
				0.8,
				-14.023,
				1,
				0.878,
				-14.023,
				0.956,
				10.844,
				1.033,
				10.844,
				1,
				1.122,
				10.844,
				1.211,
				-13.821,
				1.3,
				-13.821,
				1,
				1.378,
				-13.821,
				1.456,
				10.88,
				1.533,
				10.88,
				1,
				1.622,
				10.88,
				1.711,
				-13.834,
				1.8,
				-13.834,
				1,
				1.878,
				-13.834,
				1.956,
				10.878,
				2.033,
				10.878,
				1,
				2.122,
				10.878,
				2.211,
				-13.301,
				2.3,
				-13.301,
				1,
				2.389,
				-13.301,
				2.478,
				12.139,
				2.567,
				12.139,
				1,
				2.644,
				12.139,
				2.722,
				-12.886,
				2.8,
				-12.886,
				1,
				2.889,
				-12.886,
				2.978,
				11.594,
				3.067,
				11.594,
				1,
				3.156,
				11.594,
				3.244,
				-14.023,
				3.333,
				-14.023,
				1,
				3.411,
				-14.023,
				3.489,
				10.844,
				3.567,
				10.844,
				1,
				3.656,
				10.844,
				3.744,
				-13.821,
				3.833,
				-13.821,
				1,
				3.911,
				-13.821,
				3.989,
				10.88,
				4.067,
				10.88,
				1,
				4.156,
				10.88,
				4.244,
				-13.834,
				4.333,
				-13.834,
				1,
				4.411,
				-13.834,
				4.489,
				10.878,
				4.567,
				10.878
			]
		},
		{
			"Target": "Parameter",
			"Id": "Param17",
			"Segments": [
				0,
				6.684,
				1,
				0.033,
				14.942,
				0.067,
				21.549,
				0.1,
				21.549,
				1,
				0.178,
				21.549,
				0.256,
				-25.535,
				0.333,
				-25.535,
				1,
				0.422,
				-25.535,
				0.511,
				21.659,
				0.6,
				21.659,
				1,
				0.689,
				21.659,
				0.778,
				-25.661,
				0.867,
				-25.661,
				1,
				0.956,
				-25.661,
				1.044,
				23.196,
				1.133,
				23.196,
				1,
				1.211,
				23.196,
				1.289,
				-24.573,
				1.367,
				-24.573,
				1,
				1.456,
				-24.573,
				1.544,
				22.779,
				1.633,
				22.779,
				1,
				1.711,
				22.779,
				1.789,
				-25.637,
				1.867,
				-25.637,
				1,
				1.956,
				-25.637,
				2.044,
				21.566,
				2.133,
				21.566,
				1,
				2.211,
				21.566,
				2.289,
				-25.519,
				2.367,
				-25.519,
				1,
				2.456,
				-25.519,
				2.544,
				21.662,
				2.633,
				21.662,
				1,
				2.711,
				21.662,
				2.789,
				-25.525,
				2.867,
				-25.525,
				1,
				2.956,
				-25.525,
				3.044,
				21.655,
				3.133,
				21.655,
				1,
				3.222,
				21.655,
				3.311,
				-25.661,
				3.4,
				-25.661,
				1,
				3.489,
				-25.661,
				3.578,
				23.196,
				3.667,
				23.196,
				1,
				3.744,
				23.196,
				3.822,
				-24.573,
				3.9,
				-24.573,
				1,
				3.989,
				-24.573,
				4.078,
				22.779,
				4.167,
				22.779,
				1,
				4.244,
				22.779,
				4.322,
				-25.637,
				4.4,
				-25.637,
				1,
				4.456,
				-25.636,
				4.511,
				-7.198,
				4.567,
				6.631
			]
		},
		{
			"Target": "Parameter",
			"Id": "Param18",
			"Segments": [
				0,
				-22.749,
				1,
				0.011,
				-24.702,
				0.022,
				-25.842,
				0.033,
				-25.842,
				1,
				0.111,
				-25.842,
				0.189,
				28.592,
				0.267,
				28.592,
				1,
				0.356,
				28.592,
				0.444,
				-25.604,
				0.533,
				-25.604,
				1,
				0.622,
				-25.604,
				0.711,
				28.68,
				0.8,
				28.68,
				1,
				0.878,
				28.68,
				0.956,
				-28.596,
				1.033,
				-28.596,
				1,
				1.122,
				-28.596,
				1.211,
				28.985,
				1.3,
				28.985,
				1,
				1.378,
				28.985,
				1.456,
				-26.224,
				1.533,
				-26.224,
				1,
				1.622,
				-26.224,
				1.711,
				30,
				1.8,
				30,
				1,
				1.889,
				30,
				1.978,
				-26.002,
				2.067,
				-26.002,
				1,
				2.144,
				-26.002,
				2.222,
				29.271,
				2.3,
				29.271,
				1,
				2.389,
				29.271,
				2.478,
				-25.542,
				2.567,
				-25.542,
				1,
				2.644,
				-25.542,
				2.722,
				29.489,
				2.8,
				29.489,
				1,
				2.889,
				29.489,
				2.978,
				-25.634,
				3.067,
				-25.634,
				1,
				3.156,
				-25.634,
				3.244,
				28.584,
				3.333,
				28.584,
				1,
				3.411,
				28.584,
				3.489,
				-28.597,
				3.567,
				-28.597,
				1,
				3.656,
				-28.597,
				3.744,
				28.997,
				3.833,
				28.997,
				1,
				3.911,
				28.997,
				3.989,
				-26.224,
				4.067,
				-26.224,
				1,
				4.156,
				-26.224,
				4.244,
				30,
				4.333,
				30,
				1,
				4.411,
				29.999,
				4.489,
				-12.877,
				4.567,
				-23.596
			]
		},
		{
			"Target": "Parameter",
			"Id": "Param19",
			"Segments": [
				0,
				25.555,
				1,
				0.056,
				11.666,
				0.111,
				-30,
				0.167,
				-30,
				1,
				0.189,
				-30,
				0.211,
				-30,
				0.233,
				-30,
				1,
				0.3,
				-30,
				0.367,
				30,
				0.433,
				30,
				1,
				0.522,
				30,
				0.611,
				-28.004,
				0.7,
				-28.004,
				1,
				0.778,
				-28.004,
				0.856,
				30,
				0.933,
				30,
				1,
				0.944,
				30,
				0.956,
				30,
				0.967,
				30,
				1,
				1.044,
				30,
				1.122,
				-30,
				1.2,
				-30,
				1,
				1.278,
				-30,
				1.356,
				30,
				1.433,
				30,
				1,
				1.444,
				30,
				1.456,
				30,
				1.467,
				30,
				1,
				1.556,
				30,
				1.644,
				-29.586,
				1.733,
				-29.586,
				1,
				1.8,
				-29.586,
				1.867,
				30,
				1.933,
				30,
				1,
				1.944,
				30,
				1.956,
				30,
				1.967,
				30,
				1,
				2.056,
				30,
				2.144,
				-30,
				2.233,
				-30,
				1,
				2.311,
				-30,
				2.389,
				30,
				2.467,
				30,
				1,
				2.556,
				30,
				2.644,
				-29.169,
				2.733,
				-29.169,
				1,
				2.811,
				-29.169,
				2.889,
				30,
				2.967,
				30,
				1,
				3.056,
				30,
				3.144,
				-28.991,
				3.233,
				-28.991,
				1,
				3.311,
				-28.991,
				3.389,
				30,
				3.467,
				30,
				1,
				3.478,
				30,
				3.489,
				30,
				3.5,
				30,
				1,
				3.578,
				30,
				3.656,
				-30,
				3.733,
				-30,
				1,
				3.811,
				-30,
				3.889,
				30,
				3.967,
				30,
				1,
				3.978,
				30,
				3.989,
				30,
				4,
				30,
				1,
				4.089,
				30,
				4.178,
				-29.575,
				4.267,
				-29.575,
				1,
				4.333,
				-29.575,
				4.4,
				30,
				4.467,
				30,
				1,
				4.478,
				30,
				4.489,
				30,
				4.5,
				30,
				1,
				4.522,
				30,
				4.544,
				26.25,
				4.567,
				20.625
			]
		},
		{
			"Target": "Parameter",
			"Id": "Param26",
			"Segments": [
				0,
				25.48,
				1,
				0.056,
				11.61,
				0.111,
				-30,
				0.167,
				-30,
				1,
				0.178,
				-30,
				0.189,
				-30,
				0.2,
				-30,
				1,
				0.289,
				-30,
				0.378,
				30,
				0.467,
				30,
				1,
				0.533,
				30,
				0.6,
				-30,
				0.667,
				-30,
				1,
				0.678,
				-30,
				0.689,
				-30,
				0.7,
				-30,
				1,
				0.789,
				-30,
				0.878,
				30,
				0.967,
				30,
				1,
				0.978,
				30,
				0.989,
				30,
				1,
				30,
				1,
				1.056,
				30,
				1.111,
				-30,
				1.167,
				-30,
				1,
				1.189,
				-30,
				1.211,
				-30,
				1.233,
				-30,
				1,
				1.322,
				-30,
				1.411,
				29.548,
				1.5,
				29.548,
				1,
				1.556,
				29.548,
				1.611,
				-30,
				1.667,
				-30,
				1,
				1.689,
				-30,
				1.711,
				-30,
				1.733,
				-30,
				1,
				1.822,
				-30,
				1.911,
				29.338,
				2,
				29.338,
				1,
				2.067,
				29.338,
				2.133,
				-30,
				2.2,
				-30,
				1,
				2.222,
				-30,
				2.244,
				-30,
				2.267,
				-30,
				1,
				2.344,
				-30,
				2.422,
				29.401,
				2.5,
				29.401,
				1,
				2.567,
				29.401,
				2.633,
				-30,
				2.7,
				-30,
				1,
				2.711,
				-30,
				2.722,
				-30,
				2.733,
				-30,
				1,
				2.822,
				-30,
				2.911,
				30,
				3,
				30,
				1,
				3.067,
				30,
				3.133,
				-30,
				3.2,
				-30,
				1,
				3.211,
				-30,
				3.222,
				-30,
				3.233,
				-30,
				1,
				3.322,
				-30,
				3.411,
				30,
				3.5,
				30,
				1,
				3.511,
				30,
				3.522,
				30,
				3.533,
				30,
				1,
				3.589,
				30,
				3.644,
				-30,
				3.7,
				-30,
				1,
				3.722,
				-30,
				3.744,
				-30,
				3.767,
				-30,
				1,
				3.856,
				-30,
				3.944,
				29.549,
				4.033,
				29.549,
				1,
				4.089,
				29.549,
				4.144,
				-30,
				4.2,
				-30,
				1,
				4.222,
				-30,
				4.244,
				-30,
				4.267,
				-30,
				1,
				4.356,
				-30,
				4.444,
				29.338,
				4.533,
				29.338,
				1,
				4.544,
				29.338,
				4.556,
				27.689,
				4.567,
				24.942
			]
		},
		{
			"Target": "Parameter",
			"Id": "Param22",
			"Segments": [
				0,
				-10.601,
				1,
				0.033,
				-12.086,
				0.067,
				-13,
				0.1,
				-13,
				1,
				0.156,
				-13,
				0.211,
				13,
				0.267,
				13,
				1,
				0.444,
				13,
				0.622,
				-13,
				0.8,
				-13,
				1,
				0.867,
				-13,
				0.933,
				13,
				1,
				13,
				1,
				1.178,
				13,
				1.356,
				-13,
				1.533,
				-13,
				1,
				1.589,
				-13,
				1.644,
				13,
				1.7,
				13,
				1,
				1.878,
				13,
				2.056,
				-13,
				2.233,
				-13,
				1,
				2.3,
				-13,
				2.367,
				13,
				2.433,
				13,
				1,
				2.611,
				13,
				2.789,
				-13,
				2.967,
				-13,
				1,
				3.033,
				-13,
				3.1,
				13,
				3.167,
				13,
				1,
				3.344,
				13,
				3.522,
				-13,
				3.7,
				-13,
				1,
				3.756,
				-13,
				3.811,
				13,
				3.867,
				13,
				1,
				4.044,
				13,
				4.222,
				-13,
				4.4,
				-13,
				0,
				4.567,
				-13
			]
		},
		{
			"Target": "Parameter",
			"Id": "Param7",
			"Segments": [
				0,
				-5.739,
				1,
				0.067,
				-0.006,
				0.133,
				11.461,
				0.2,
				11.461,
				1,
				0.278,
				11.461,
				0.356,
				-8.699,
				0.433,
				-8.699,
				1,
				0.522,
				-8.699,
				0.611,
				11.123,
				0.7,
				11.123,
				1,
				0.778,
				11.123,
				0.856,
				-8.606,
				0.933,
				-8.606,
				1,
				1.022,
				-8.606,
				1.111,
				11.301,
				1.2,
				11.301,
				1,
				1.289,
				11.301,
				1.378,
				-9.857,
				1.467,
				-9.857,
				1,
				1.544,
				-9.857,
				1.622,
				11.302,
				1.7,
				11.302,
				1,
				1.789,
				11.302,
				1.878,
				-9.268,
				1.967,
				-9.268,
				1,
				2.044,
				-9.268,
				2.122,
				11.342,
				2.2,
				11.342,
				1,
				2.289,
				11.342,
				2.378,
				-9.454,
				2.467,
				-9.454,
				1,
				2.556,
				-9.454,
				2.644,
				11.78,
				2.733,
				11.78,
				1,
				2.811,
				11.78,
				2.889,
				-8.502,
				2.967,
				-8.502,
				1,
				3.056,
				-8.502,
				3.144,
				11.072,
				3.233,
				11.072,
				1,
				3.311,
				11.072,
				3.389,
				-8.649,
				3.467,
				-8.649,
				1,
				3.556,
				-8.649,
				3.644,
				11.31,
				3.733,
				11.31,
				1,
				3.822,
				11.31,
				3.911,
				-9.85,
				4,
				-9.85,
				1,
				4.078,
				-9.85,
				4.156,
				11.302,
				4.233,
				11.302,
				1,
				4.322,
				11.302,
				4.411,
				-9.269,
				4.5,
				-9.269,
				1,
				4.522,
				-9.269,
				4.544,
				-7.587,
				4.567,
				-5.183
			]
		},
		{
			"Target": "Parameter",
			"Id": "Param10",
			"Segments": [
				0,
				18.784,
				1,
				0.011,
				19.757,
				0.022,
				20.305,
				0.033,
				20.305,
				1,
				0.111,
				20.305,
				0.189,
				-25.65,
				0.267,
				-25.65,
				1,
				0.356,
				-25.65,
				0.444,
				18.892,
				0.533,
				18.892,
				1,
				0.611,
				18.892,
				0.689,
				-25.473,
				0.767,
				-25.473,
				1,
				0.856,
				-25.473,
				0.944,
				19.05,
				1.033,
				19.05,
				1,
				1.111,
				19.05,
				1.189,
				-25.596,
				1.267,
				-25.596,
				1,
				1.356,
				-25.596,
				1.444,
				19.731,
				1.533,
				19.731,
				1,
				1.611,
				19.731,
				1.689,
				-24.344,
				1.767,
				-24.344,
				1,
				1.856,
				-24.344,
				1.944,
				20.197,
				2.033,
				20.197,
				1,
				2.111,
				20.197,
				2.189,
				-24.396,
				2.267,
				-24.396,
				1,
				2.367,
				-24.396,
				2.467,
				20.347,
				2.567,
				20.347,
				1,
				2.644,
				20.347,
				2.722,
				-25.616,
				2.8,
				-25.616,
				1,
				2.889,
				-25.616,
				2.978,
				18.908,
				3.067,
				18.908,
				1,
				3.144,
				18.908,
				3.222,
				-25.476,
				3.3,
				-25.476,
				1,
				3.389,
				-25.476,
				3.478,
				19.047,
				3.567,
				19.047,
				1,
				3.644,
				19.047,
				3.722,
				-25.596,
				3.8,
				-25.596,
				1,
				3.889,
				-25.596,
				3.978,
				19.731,
				4.067,
				19.731,
				1,
				4.144,
				19.731,
				4.222,
				-24.344,
				4.3,
				-24.344,
				1,
				4.389,
				-24.344,
				4.478,
				20.197,
				4.567,
				20.197
			]
		},
		{
			"Target": "Parameter",
			"Id": "Param9",
			"Segments": [
				0,
				-14.347,
				1,
				0.067,
				-0.014,
				0.133,
				28.652,
				0.2,
				28.652,
				1,
				0.278,
				28.652,
				0.356,
				-21.748,
				0.433,
				-21.748,
				1,
				0.522,
				-21.748,
				0.611,
				27.808,
				0.7,
				27.808,
				1,
				0.778,
				27.808,
				0.856,
				-21.515,
				0.933,
				-21.515,
				1,
				1.022,
				-21.515,
				1.111,
				28.253,
				1.2,
				28.253,
				1,
				1.289,
				28.253,
				1.378,
				-24.643,
				1.467,
				-24.643,
				1,
				1.544,
				-24.643,
				1.622,
				28.254,
				1.7,
				28.254,
				1,
				1.789,
				28.254,
				1.878,
				-23.171,
				1.967,
				-23.171,
				1,
				2.044,
				-23.171,
				2.122,
				28.354,
				2.2,
				28.354,
				1,
				2.289,
				28.354,
				2.378,
				-23.636,
				2.467,
				-23.636,
				1,
				2.556,
				-23.636,
				2.644,
				29.45,
				2.733,
				29.45,
				1,
				2.811,
				29.45,
				2.889,
				-21.254,
				2.967,
				-21.254,
				1,
				3.056,
				-21.254,
				3.144,
				27.681,
				3.233,
				27.681,
				1,
				3.311,
				27.681,
				3.389,
				-21.623,
				3.467,
				-21.623,
				1,
				3.556,
				-21.623,
				3.644,
				28.276,
				3.733,
				28.276,
				1,
				3.822,
				28.276,
				3.911,
				-24.625,
				4,
				-24.625,
				1,
				4.078,
				-24.625,
				4.156,
				28.254,
				4.233,
				28.254,
				1,
				4.322,
				28.254,
				4.411,
				-23.173,
				4.5,
				-23.173,
				1,
				4.522,
				-23.173,
				4.544,
				-18.967,
				4.567,
				-12.958
			]
		}
	]
}